Source/UePack.py
Source/__init__.py
Unreal_Engine_Packer-1.2.dist-info/METADATA
Unreal_Engine_Packer-1.2.dist-info/WHEEL
Unreal_Engine_Packer-1.2.dist-info/entry_points.txt
Unreal_Engine_Packer-1.2.dist-info/top_level.txt
Unreal_Engine_Packer-1.2.dist-info/RECORD
