Metadata-Version: 2.1
Name: Unreal-Engine-Packer
Version: 1.2
Summary: A commandline tool to automatically package Unreal Engine projects or plugins
Home-page: https://github.com/R00tDroid/UnrealPacker
Author: R00tDroid
License: MIT
